PySensorMQTT/__init__.py
PySensorMQTT/mqtt_sensor.py
PySensorMQTT/sensors/__init__.py
PySensorMQTT/sensors/base.py
PySensorMQTT/sensors/humidity_air.py
PySensorMQTT/sensors/humidity_soil.py
PySensorMQTT/sensors/light.py
PySensorMQTT/sensors/manager.py
PySensorMQTT/sensors/modulo_rele.py
PySensorMQTT/sensors/motion.py
PySensorMQTT/sensors/temperature.py
PySensor_MQTT-0.3.5.dist-info/LICENSE
PySensor_MQTT-0.3.5.dist-info/METADATA
PySensor_MQTT-0.3.5.dist-info/WHEEL
PySensor_MQTT-0.3.5.dist-info/top_level.txt
PySensor_MQTT-0.3.5.dist-info/RECORD
